Workbook

Sheet Cover Page
D5: Caterpillar Inc.

Sheet Historic FCFF
B2: Historic FCFF
B3: ='Cover Page'!D5&" | "&TEXT(TODAY(),"mmmm d, yyyy") -> Caterpillar Inc. | July 1, 2026
B5: USD' millions
D8: 2021 | E8: =+D8+1 -> 2022 | F8: =+E8+1 -> 2023 | G8: =+F8+1 -> 2024 | H8: =+G8+1 -> 2025
B10: Net Income | D10: =+'Input Data'!F31 -> 6489 | E10: =+'Input Data'!G31 -> 6705 | F10: =+'Input Data'!H31 -> 10335 | G10: =+'Input Data'!I31 -> 10792 | H10: =+'Input Data'!J31 -> 8884
B11: Add: Non cash charges | D11: =+D12+D13 -> 2352 | E11: =+E12+E13 -> 2219 | F11: =+F12+F13 -> 2144 | G11: =+G12+G13 -> 2153 | H11: =+H12+H13 -> 2262
B12: D&A | D12: =+'Input Data'!F15 -> 2352 | E12: =+'Input Data'!G15 -> 2219 | F12: =+'Input Data'!H15 -> 2144 | G12: =+'Input Data'!I15 -> 2153 | H12: =+'Input Data'!J15 -> 2262
B13: Share based comp…
B14: Less: Changes in Working Capital | D14: =+'Input Data'!F76 -> -1846 | E14: =+'Input Data'!G76 -> -1927 | F14: =+'Input Data'!H76 -> -20 | G14: =+'Input Data'!I76 -> -1234 | H14: =+'Input Data'!J76 -> -16
B15: Less: Capex | D15: =+'Input Data'!F81*-1 -> 1093 | E15: =+'Input Data'!G81*-1 -> 1296 | F15: =+'Input Data'!H81*-1 -> 1597 | G15: =+'Input Data'!I81*-1 -> 1988 | H15: =+'Input Data'!J81*-1 -> 2821
B16: FCF | D16: =+D10+D11-D14-D15 -> 9594 | E16: =+E10+E11-E14-E15 -> 9555 | F16: =+F10+F11-F14-F15 -> 10902 | G16: =+G10+G11-G14-G15 -> 12191 | H16: =+H10+H11-H14-H15 -> 8341
I18: Average
B19: Revenue | D19: =+'Input Data'!F9 -> 50971 | E19: =+'Input Data'!G9 -> 59427 | F19: =+'Input Data'!H9 -> 67060 | G19: =+'Input Data'!I9 -> 64809 | H19: =+'Input Data'!J9 -> 67589
B20: Revenue growth | E20: =+(E19-D19)/D19 -> 0.16589826 | F20: =+(F19-E19)/E19 -> 0.1284433 | G20: =+(G19-F19)/F19 -> -0.033566955 | H20: =+(H19-G19)/G19 -> 0.042895277 | I20: =+AVERAGE(E20:H20) -> 0.075917469
B21: FCF margin | D21: =+D16/D19 -> 0.18822468 | E21: =+E16/E19 -> 0.1607855 | F21: =+F16/F19 -> 0.16257083 | G21: =+G16/G19 -> 0.18810659 | H21: =+H16/H19 -> 0.12340766 | I21: =+AVERAGE(D21:H21) -> 0.16461905
B22: FCF growth | E22: =+(E16-D16)/D16 -> -0.0040650406 | F22: =+(F16-E16)/E16 -> 0.14097331 | G22: =+(G16-F16)/F16 -> 0.11823519 | H22: =+(H16-G16)/G16 -> -0.31580674
B23: FCF ROC | I23: =+H16/(SUM('Input Data'!J43,'Input Data'!J45:J46)+('Input Data'!J42-'Input Data'!J55)) -> 0.18286453
B25: Current Assets | D25: =+'Input Data'!F42 -> 43455 | E25: =+'Input Data'!G42 -> 43785 | F25: =+'Input Data'!H42 -> 46949 | G25: =+'Input Data'!I42 -> 45682 | H25: =+'Input Data'!J42 -> 52485
B26: Current liabilities | D26: =+'Input Data'!F55 -> 29847 | E26: =+'Input Data'!G55 -> 31531 | F26: =+'Input Data'!H55 -> 34728 | G26: =+'Input Data'!I55 -> 32272 | H26: =+'Input Data'!J55 -> 36558
B27: Working Capital | D27: =+D25-D26 -> 13608 | E27: =+E25-E26 -> 12254 | F27: =+F25-F26 -> 12221 | G27: =+G25-G26 -> 13410 | H27: =+H25-H26 -> 15927
B28: Change Working Capital | E28: =+E27-D27 -> -1354 | F28: =+F27-E27 -> -33 | G28: =+G27-F27 -> 1189 | H28: =+H27-G27 -> 2517

Sheet Estimated FCFF
B2: Estimated FCFF
B3: ='Cover Page'!D5&" | "&TEXT(TODAY(),"mmmm d, yyyy") -> Caterpillar Inc. | July 1, 2026
B5: USD' millions
D7: 2026 | E7: =+D7+1 -> 2027 | F7: =+E7+1 -> 2028 | G7: =+F7+1 -> 2029 | H7: =+G7+1 -> 2030 | I7: =+H7+1 -> 2031 | J7: =+I7+1 -> 2032
B9: Revenue | D9: =+'Historic FCFF'!H19*(1+'Estimated FCFF'!D10) -> 72725.764 | E9: =+D9*(1+E10) -> 77816.567 | F9: =+E9*(1+F10) -> 81707.396 | G9: =+F9*(1+G10) -> 85792.766 | H9: =+G9*(1+H10) -> 90082.404 | I9: =+H9*(1+I10) -> 94586.524 | J9: =+I9*(1+J10) -> 99315.85
B10: Revenue growth | D10: 0.076 | E10: 0.07 | F10: 0.05 | G10: 0.05 | H10: 0.05 | I10: 0.05 | J10: 0.05
B11: FCF margin | D11: 0.141 | E11: 0.141 | F11: 0.141 | G11: 0.141 | H11: 0.141 | I11: 0.141 | J11: 0.141
B12: FCF | D12: =+D9*D11 -> 10254.333 | E12: =+E9*E11 -> 10972.136 | F12: =+F9*F11 -> 11520.743 | G12: =+G9*G11 -> 12096.78 | H12: =+H9*H11 -> 12701.619 | I12: =+I9*I11 -> 13336.7 | J12: =+J9*J11 -> 14003.535
B13: Terminal | J13: =+(J12*(1+D17))/(D16-D17) -> 212112.37
B14: FCFF | D14: =+SUM(D12:D13) -> 10254.333 | E14: =+SUM(E12:E13) -> 10972.136 | F14: =+SUM(F12:F13) -> 11520.743 | G14: =+SUM(G12:G13) -> 12096.78 | H14: =+SUM(H12:H13) -> 12701.619 | I14: =+SUM(I12:I13) -> 13336.7 | J14: =+SUM(J12:J13) -> 226115.9
B16: WACC | D16: 0.098
B17: Terminal growth rate | D17: 0.03
B19: Enterprise Value (XNPV) | D19: =+XNPV(D16,D14:J14,D7:J7) -> 296602.9
B20: Add: Cash | D20: =+'Input Data'!J37 -> 9980
B21: Less: Debt | D21: =+'Input Data'!J56+'Input Data'!J53+'Input Data'!J50 -> 43330
B22: Equity Value | D22: =+D19+D20-D21 -> 263252.9
B24: Shares Outstand… | D24: 478
B25: Equity Value/Share | D25: =+D22/D24 -> 550.73828

Sheet Input Data
B2: Group Financial Statements
B4: Income Statement | F4: 2021 | G4: =+F4+1 -> 2022 | H4: =+G4+1 -> 2023 | I4: =+H4+1 -> 2024 | J4: =+I4+1 -> 2025 | K4: TTM
B6: Sales and Revenues:
B7: Sales (Machinery, Energy & Transp./Power) | F7: 48188 | G7: 56574 | H7: 63869 | I7: 61363 | J7: 63980
B8: Revenues of Financial Products | F8: 2783 | G8: 2853 | H8: 3191 | I8: 3446 | J8: 3609
B9: Total Sales and Revenues | F9: 50971 | G9: 59427 | H9: 67060 | I9: 64809 | J9: 67589
B11: Operating Costs:
B12: Cost of goods sold | F12: 35513 | G12: 41350 | H12: 42767 | I12: 40199 | J12: 44752
B13: SG&A expenses | F13: 5365 | G13: 5651 | H13: 6371 | I13: 6667 | J13: 6985
B14: SG&A | F14: 3013 | G14: 3432 | H14: 4227 | I14: 4514 | J14: 4723
B15: D&A | F15: 2352 | G15: 2219 | H15: 2144 | I15: 2153 | J15: 2262
B16: R&D expenses | F16: 1686 | G16: 1814 | H16: 2108 | I16: 2107 | J16: 2148
B17: Interest expense of Financial Products | F17: 455 | G17: 565 | H17: 1030 | I17: 1286 | J17: 1359
B18: Goodwill impairment charge | F18: 0 | G18: 925 | H18: 0 | I18: 0 | J18: 0
B19: Other operating (income) expenses | F19: 1074 | G19: 1218 | H19: 1818 | I19: 1478 | J19: 1194
B20: Total Operating Costs | F20: 44093 | G20: 51523 | H20: 54094 | I20: 51737 | J20: 56438
B22: Operating Profit | F22: 6878 | G22: 7904 | H22: 12966 | I22: 13072 | J22: 11151
B24: Interest exp. (excl. Financial Products) | F24: 488 | G24: 443 | H24: 511 | I24: 512 | J24: 502
B25: Other income (expense) | F25: 1814 | G25: 1291 | H25: 595 | I25: 813 | J25: 892
... B34: Balance Sheet | F34: 2021 | G34: 2022 | H34: 2023 | I34: 2024 | J34: 2025
B36: Assets
B37: Cash and cash equivalents | F37: 9254 | G37: 7004 | H37: 6978 | I37: 6889 | J37: 9980
B38: Receivables – trade and other | F38: 8477 | G38: 8856 | H38: 9310 | I38: 9282 | J38: 10920
B39: Receivables – finance | F39: 8898 | G39: 9013 | H39: 9510 | I39: 9565 | J39: 10649
B40: Inventories | F40: 14038 | G40: 16270 | H40: 16565 | I40: 16827 | J40: 18135
B41: Other current assets | F41: 2788 | G41: 2642 | H41: 4586 | I41: 3119 | J41: 2801
B42: Total current assets | F42: 43455 | G42: 43785 | H42: 46949 | I42: 45682 | J42: 52485
B43: Property, plant and equipment – net | F43: 12090 | G43: 12028 | H43: 12680 | I43: 13361 | J43: 15140
B44: Long-term receivables (Trade & Fin.) | F44: 13911 | G44: 13278 | H44: 13902 | I44: 14467 | J44: 16414
B45: Goodwill & Intangible assets | F45: 7366 | G45: 6046 | H45: 5872 | I45: 5640 | J45: 5562
B46: Other non-current assets | F46: 5971 | G46: 6806 | H46: 8073 | I46: 8614 | J46: 8984
B47: Total assets | F47: 82793 | G47: 81943 | H47: 87476 | I47: 87764 | J47: 98585
B49: Liabilities
B50: Short-term borrowings | F50: 5404 | G50: 5957 | H50: 4643 | I50: 4393 | J50: 5514
B51: Accounts payable | F51: 8154 | G51: 8689 | H51: 7906 | I51: 7675 | J51: 8968
B52: Accrued expenses & wages | F52: 5999 | G52: 6393 | H52: 7715 | I52: 7634 | J52: 8141
B53: Long-term debt due within 1 yr | F53: 6352 | G53: 5322 | H53: 8763 | I53: 6665 | J53: 7120
B54: Other current liabilities | F54: 3938 | G54: 5170 | H54: 5701 | I54: 5905 | J54: 6815
B55: Total current liabilities | F55: 29847 | G55: 31531 | H55: 34728 | I55: 32272 | J55: 36558
B56: Long-term debt due after 1 yr | F56: 26033 | G56: 25714 | H56: 24472 | I56: 27351 | J56: 30696
B57: Other non-current liabilities | F57: 10397 | G57: 8807 | H57: 8773 | I57: 8647 | J57: 10013
B58: Total liabilities | F58: 66277 | G58: 66052 | H58: 67973 | I58: 68270 | J58: 77267
B60: Shareholders' Equity
B61: Common stock | F61: 6398 | G61: 6560 | H61: 6403 | I61: 6941 | J61: 7181
B62: Treasury stock | F62: -27643 | G62: -31748 | H62: -36339 | I62: -44331 | J62: -49539
B63: Profit employed in the business | F63: 39282 | G63: 43514 | H63: 51250 | I63: 59352 | J63: 65448
B64: Accumulated other comp. loss | F64: -1553 | G64: -2457 | H64: -1820 | I64: -2471 | J64: -1772
B65: Noncontrolling interests | F65: 32 | G65: 22 | H65: 9 | I65: 3 | J65: —
B66: Total shareholders' equity | F66: 16516 | G66: 15891 | H66: 19503 | I66: 19494 | J66: 21318
B67: Total liab. and equity | F67: 82793 | G67: 81943 | H67: 87476 | I67: 87764 | J67: 98585
B70: Cash Flow Statement | F70: 2021 | G70: 2022 | H70: 2023 | I70: 2024 | J70: 2025
B73: Operating Activities:
B74: Profit (Consolidated & Affiliated) | F74: 6493 | G74: 6704 | H74: 10332 | I74: 10788 | J74: 8882
B75: Depreciation and Amortization | F75: 2352 | G75: 2219 | H75: 2144 | I75: 2153 | J75: 2262
B76: Changes in Assets/Liabilities (Net) | F76: -1846 | G76: -1927 | H76: -20 | I76: -1234 | J76: -16
B77: Other adjustments | F77: 199 | G77: 770 | H77: 429 | I77: 328 | J77: 611
B78: Net Cash from Operating Activities | F78: 7198 | G78: 7766 | H78: 12885 | I78: 12035 | J78: 11739
B80: Investing Activities:
B81: Capital Expenditures (Excl. Leased) | F81: -1093 | G81: -1296 | H81: -1597 | I81: -1988 | J81: -2821
B82: Additions to Finance Receivables | F82: -13002 | G82: -13239 | H82: -15161 | I82: -15409 | J82: -15329
B83: Collections of Finance Receivables | F83: 12430 | G83: 13177 | H83: 14034 | I83: 13608 | J83: 13515
B84: Other Investing (Net) | F84: -1419 | G84: -1183 | H84: -3147 | I84: 1336 | J84: -72
B85: Net Cash from Investing Activities | F85: -3084 | G85: -2541 | H85: -5871 | I85: -2453 | J85: -4707
B87: Financing Activities:
B88: Dividends Paid | F88: -2332 | G88: -2440 | H88: -2563 | I88: -2646 | J88: -2749
B89: Share Repurchases (Common Stock) | F89: -2668 | G89: -4230 | H89: -4975 | I89: -7697 | J89: -5190
B90: Proceeds from Debt Issued | F90: 6989 | G90: 6674 | H90: 8257 | I90: 10283 | J90: 11105
B91: Payments on Debt | F91: -9796 | G91: -7728 | H91: -6318 | I91: -9316 | J91: -8081
B92: Other Financing (Net) | F92: 3619 | G92: 443 | H92: -1333 | I92: -189 | J92: 1016
B93: Net Cash from Financing Activities | F93: -4188 | G93: -7281 | H93: -6932 | I93: -9565 | J93: -3899
B95: Net Change in Cash | F95: -103 | G95: -2250 | H95: -28 | I95: -89 | J95: 3090
B96: Cash Balance (End of Year) | F96: 9263 | G96: 7013 | H96: 6985 | I96: 6896 | J96: 9986
